<?xml version="1.0" encoding="UTF-8"?>
<odoo>

    <!-- Menú raíz propio -->
    <menuitem id="menu_hr_payroll_root"
              name="Nómina"
              parent="hr.menu_hr_root"
              sequence="10"
              groups="hr.group_hr_user"/>

    <!-- MENÚS PRINCIPALES -->
    <menuitem id="menu_cl_hr_payroll_base" name="Nómina RRHH"
              parent="menu_hr_payroll_root" sequence="2"
              groups="hr_payroll.group_hr_payroll_user"/>

    <menuitem id="menu_cl_hr_payroll_addons"
              name="Adicionales Nómina"
              parent="menu_hr_payroll_root" sequence="3"/>

    <menuitem id="menu_cl_hr_payroll_indicators" name="Previsión"
              parent="menu_hr_payroll_root" sequence="4"
              groups="hr_payroll.group_hr_payroll_user"/>

    <menuitem id="menu_cl_hr_payroll_master_data"
              name="Master Data"
              parent="menu_hr_payroll_root" sequence="5"
              groups="hr_payroll.group_hr_payroll_user"/>

    <menuitem id="menu_cl_hr_payroll_reports"
              name="Reports"
              parent="menu_hr_payroll_root" sequence="6"
              groups="hr_payroll.group_hr_payroll_user"/>

    <!-- (Opcional) Configuración local -->
    <menuitem id="menu_cl_hr_payroll_configuration"
              name="Chilean Configuration"
              parent="menu_hr_payroll_root" sequence="7"
              groups="hr_payroll.group_hr_payroll_user"/>

    <!-- SUBMENÚS -->
    <menuitem id="hr_menu_contract"
              action="hr_contract.action_hr_contract"
              parent="menu_hr_payroll_root" sequence="1"
              groups="hr_contract.group_hr_contract_manager"/>

    <!-- Reubicar menús existentes de nómina -->
    <menuitem
        id="hr_payroll.menu_hr_payslip_run"
        name="Lotes de Nómina"
        parent="menu_cl_hr_payroll_base"
        action="l10n_cl_simpledigital_payroll.action_hr_payslip_run_tree"
        sequence="10"
        groups="hr_payroll.group_hr_payroll_user"/>
    
    <!-- DATOS MAESTROS -->
    <menuitem id="cl_hr_menu_hr_job_tree"
              action="hr.action_hr_job"
              parent="menu_cl_hr_payroll_master_data" sequence="2"
              groups="hr_payroll.group_hr_payroll_user"/>

    <menuitem id="cl_hr_menu_hr_department_tree"
              action="hr.open_module_tree_department"
              parent="menu_cl_hr_payroll_master_data" sequence="3"
              groups="hr.group_hr_user"/>

    <menuitem id="cl_hr_menu_view_employee_category_form"
              action="hr.open_view_categ_form"
              parent="menu_cl_hr_payroll_master_data" sequence="4"
              groups="hr.group_hr_user"/>

    <menuitem id="cl_hr_partner_bank_account_tree_view"
              action="base.action_res_partner_bank_account_form"
              parent="menu_cl_hr_payroll_master_data" sequence="5"
              groups="hr_payroll.group_hr_payroll_user"/>

    <menuitem id="cl_hr_account_analytic_def_account"
              action="analytic.action_account_analytic_account_form"
              parent="menu_cl_hr_payroll_master_data" sequence="6"
              groups="analytic.group_analytic_accounting"/>

    <menuitem id="cl_hr_account_analytic_group_menu"
              action="analytic.account_analytic_group_action"
              parent="menu_cl_hr_payroll_master_data" sequence="7"
              groups="analytic.group_analytic_accounting"/>

    <menuitem id="cl_hr_resource_calendar_form"
              action="resource.action_resource_calendar_form"
              parent="menu_cl_hr_payroll_master_data" sequence="8"
              groups="hr_payroll.group_hr_payroll_user"/>

    <menuitem id="cl_hr_resource_calendar_leave_tree"
              action="resource.action_resource_calendar_leave_tree"
              parent="menu_cl_hr_payroll_master_data" sequence="9"
              groups="hr_payroll.group_hr_payroll_user"/>

    <!-- REPORTES -->
    <menuitem id="menu_cl_report_previred"
              name="Previred"
              action="action_wizard_export_csv_previred_tree_view"
              parent="menu_cl_hr_payroll_reports"
              sequence="1"
              groups="hr_payroll.group_hr_payroll_user"/>

    <menuitem id="menu_cl_report_salary_book"
              name="Libro de Remuneraciones Electrónico"
              action="action_report_hrsalarybymonth"
              parent="menu_cl_hr_payroll_reports"
              sequence="2"
              groups="hr_payroll.group_hr_payroll_user"/>

    <menuitem id="menu_cl_report_payslip"
              name="Nómina"
              action="action_report_hr_payslip"
              parent="menu_cl_hr_payroll_reports"
              sequence="3"
              groups="hr_payroll.group_hr_payroll_user"/>

    <menuitem id="menu_cl_report_account_centralized"
              name="Pago de Nómina / Centralización"
              action="account_centralized_export_action"
              parent="menu_cl_hr_payroll_reports"
              sequence="4"
              groups="hr_payroll.group_hr_payroll_user"/>

</odoo>
